[
  {
    "label": "HTML",
    "data": ["Semantic Markup", "Cross browser compatability", "Modern HTML5 tags and uses", "Accesability Markup"]
  },
  {
    "label": "CSS and UX",
    "data": ["Sass", "Flexbox", "Bootstrap", "Responsive Design", "Mobile First Design", "Angular Material design framework", "Materialize library"]
  },
  {
    "label": "Javascript",
    "data": ["ECMA6 Script", "Vanilla Javascript", "TypeScript"]
  },
  {
    "label": "Front End Frameworks",
    "data": ["Angular (versions 2 - 6)", "AngularJS (version 1.6)"]
  },
  {
    "label": "Libraries",
    "data": ["jQuery", "Lodash", "Moment", "and many more."]
  },
  {
    "label": "Backend",
    "data": ["Node.js", "Express", "MongoDB", "Mongoose", "ejs"]
  },
  {
    "Label": "Devops",
    "data": ["AWS - launching instances and running ubuntu/nginx servers, S3, Route 53", "Heroku - launching instances from Git", "Firebase - real time databases and storage"]
  },
  {
    "label": "Version Control",
    "data": ["Git", "Github"]
  },
  {
    "label": "General Skills",
    "data": ["JIRA", "Agile/Scrum", "Trello", "Slack", "Asana"]
  },
  {
    "label": "Soft Skills",
    "data": ["Team management and leadership - I have lead teams of up to 5 in the past", "Client Communication - Able to communicate with clients comfortably and explain technical concepts in a nontechnical way"]
  }
]
